st2sdk/__init__.py
st2sdk/app.py
st2sdk/shell.py
st2sdk/templates/LICENSE
st2sdk/templates/README.md
st2sdk/templates/config.yaml
st2sdk/templates/pack.yaml
st2sdk-0.5.2.data/scripts/common.sh
st2sdk-0.5.2.data/scripts/st2-check-print-pack-tests-coverage
st2sdk-0.5.2.data/scripts/st2-check-pylint-pack
st2sdk-0.5.2.data/scripts/st2-check-register-pack-resources
st2sdk-0.5.2.data/scripts/st2-check-validate-json-file
st2sdk-0.5.2.data/scripts/st2-check-validate-pack-example-config
st2sdk-0.5.2.data/scripts/st2-check-validate-pack-metadata-exists
st2sdk-0.5.2.data/scripts/st2-check-validate-yaml-file
st2sdk-0.5.2.data/scripts/st2.tests.conf
st2sdk-0.5.2.dist-info/LICENSE
st2sdk-0.5.2.dist-info/METADATA
st2sdk-0.5.2.dist-info/WHEEL
st2sdk-0.5.2.dist-info/entry_points.txt
st2sdk-0.5.2.dist-info/top_level.txt
st2sdk-0.5.2.dist-info/RECORD
