Metadata-Version: 2.1
Name: st2sdk
Version: 0.5.2
Summary: Various tools and utilities which aid with StackStorm pack development.
Home-page: http://www.stackstorm.com
Author: StackStorm
Author-email: info@stackstorm.com
License: Apache License (2.0)
Platform: UNKNOWN
Classifier: Development Status :: 4 - Beta
Classifier: Intended Audience :: Information Technology
Classifier: Intended Audience :: System Administrators
Classifier: License :: OSI Approved :: Apache Software License
Classifier: Operating System :: POSIX :: Linux
Classifier: Programming Language :: Python
Classifier: Programming Language :: Python :: 2
Classifier: Programming Language :: Python :: 2.6
Classifier: Programming Language :: Python :: 2.7
Requires-Dist: six (==1.12.0)
Requires-Dist: jinja2 (==2.10.1)
Requires-Dist: cmd2 (<0.10,>=0.9.i5)
